src/__init__.py
src/actions/__init__.py
src/actions/ethdo.py
src/actions/portal.py
src/classes/__init__.py
src/classes/daemon.py
src/classes/database.py
src/classes/trigger.py
src/commands/__init__.py
src/commands/change_maintainer.py
src/commands/check_wallet.py
src/commands/config.py
src/commands/decrease_wallet.py
src/commands/delegate.py
src/commands/deposit.py
src/commands/increase_wallet.py
src/commands/run.py
src/commands/set_fallback.py
src/common/__init__.py
src/common/attribute_dict.py
src/common/loggable.py
src/daemons/__init__.py
src/daemons/block_daemon.py
src/daemons/event_daemon.py
src/daemons/time_daemon.py
src/database/__init__.py
src/database/events.py
src/database/pools.py
src/database/validators.py
src/exceptions/__init__.py
src/exceptions/actions/__init__.py
src/exceptions/actions/ethdo.py
src/exceptions/actions/portal.py
src/exceptions/classes/__init__.py
src/exceptions/classes/daemon.py
src/exceptions/classes/database.py
src/exceptions/daemons/__init__.py
src/exceptions/daemons/event_daemon.py
src/exceptions/globals/__init__.py
src/exceptions/globals/config.py
src/exceptions/globals/sdk.py
src/exceptions/triggers/__init__.py
src/exceptions/triggers/exit_request_trigger.py
src/exceptions/utils/__init__.py
src/exceptions/utils/gas.py
src/exceptions/utils/notify.py
src/globals/__init__.py
src/globals/config.py
src/globals/constants.py
src/globals/sdk.py
src/helpers/__init__.py
src/helpers/event.py
src/helpers/portal.py
src/helpers/validator.py
src/main.py
src/setup.py
src/triggers/__init__.py
src/triggers/block/__init__.py
src/triggers/event/__init__.py
src/triggers/event/alienated_trigger.py
src/triggers/event/delegation_trigger.py
src/triggers/event/deposit_trigger.py
src/triggers/event/exit_request_trigger.py
src/triggers/event/fallback_operator_trigger.py
src/triggers/event/id_initiated_trigger.py
src/triggers/event/stake_proposal_trigger.py
src/triggers/event/stake_trigger.py
src/triggers/event/verification_trigger.py
geonius-1.6.0.dist-info/LICENSE
geonius-1.6.0.dist-info/METADATA
geonius-1.6.0.dist-info/WHEEL
geonius-1.6.0.dist-info/entry_points.txt
geonius-1.6.0.dist-info/RECORD
