Metadata-Version: 2.1
Name: geonius
Version: 1.6.0
Summary: Geonius is a daemonic script that allows Node Operators to automate their operations on geodefi Operator Marketplace
Author: 0xicebear
Author-email: admin@geode.fi
Requires-Python: >=3.8,<3.13
Classifier: Programming Language :: Python :: 3
Classifier: Programming Language :: Python :: 3.8
Classifier: Programming Language :: Python :: 3.9
Classifier: Programming Language :: Python :: 3.10
Classifier: Programming Language :: Python :: 3.11
Classifier: Programming Language :: Python :: 3.12
Requires-Dist: click (>=8.1.7,<9.0.0)
Requires-Dist: geodefi (>=3.2.0,<4.0.0)
Requires-Dist: python-dotenv (>=1.0.1,<2.0.0)
